[
 {
  "docstatus": 0,
  "doctype": "Facilities",
  "facility": "Landscaping ",
  "modified": "2025-01-03 11:42:05.537387",
  "name": 8672
 },
 {
  "docstatus": 0,
  "doctype": "Facilities",
  "facility": "Swimming Pool",
  "modified": "2025-01-03 11:42:05.554093",
  "name": 8673
 },
 {
  "docstatus": 0,
  "doctype": "Facilities",
  "facility": "Gym",
  "modified": "2025-01-03 11:42:05.568646",
  "name": 8674
 },
 {
  "docstatus": 0,
  "doctype": "Facilities",
  "facility": "Kids Area",
  "modified": "2025-01-03 11:42:05.585196",
  "name": 8675
 },
 {
  "docstatus": 0,
  "doctype": "Facilities",
  "facility": "Mall",
  "modified": "2025-01-03 11:42:05.601139",
  "name": 8676
 },
 {
  "docstatus": 0,
  "doctype": "Facilities",
  "facility": "Nursery",
  "modified": "2025-01-03 11:42:05.617950",
  "name": 8677
 },
 {
  "docstatus": 0,
  "doctype": "Facilities",
  "facility": "Security",
  "modified": "2025-01-03 11:42:05.636441",
  "name": 8678
 },
 {
  "docstatus": 0,
  "doctype": "Facilities",
  "facility": "CCTV",
  "modified": "2025-01-03 11:42:05.650518",
  "name": 8679
 },
 {
  "docstatus": 0,
  "doctype": "Facilities",
  "facility": "House Keeping",
  "modified": "2025-01-03 11:42:05.665346",
  "name": 8680
 },
 {
  "docstatus": 0,
  "doctype": "Facilities",
  "facility": "Maintenance",
  "modified": "2025-01-03 11:42:05.680958",
  "name": 8681
 },
 {
  "docstatus": 0,
  "doctype": "Facilities",
  "facility": "Play Ground",
  "modified": "2025-01-03 11:42:05.696383",
  "name": 8682
 },
 {
  "docstatus": 0,
  "doctype": "Facilities",
  "facility": "Spa",
  "modified": "2025-01-03 11:42:05.714041",
  "name": 8683
 },
 {
  "docstatus": 0,
  "doctype": "Facilities",
  "facility": "Lounge",
  "modified": "2025-01-03 11:42:05.730958",
  "name": 8684
 }
]